tdxtrader/__init__.py
tdxtrader/anis.py
tdxtrader/file.py
tdxtrader/index.py
tdxtrader/logger.py
tdxtrader/order.py
tdxtrader/trader.py
tdxtrader/utils.py
tdxtrader-0.4.5.dist-info/LICENSE
tdxtrader-0.4.5.dist-info/WHEEL
tdxtrader-0.4.5.dist-info/METADATA
tdxtrader-0.4.5.dist-info/RECORD
