Metadata-Version: 2.3
Name: tdxtrader
Version: 0.4.5
Summary: 
Author-email: myc <mayuanchi1029@gmail.com>
Classifier: License :: OSI Approved :: MIT License
Requires-Dist: xtquant
Project-URL: Home, https://github.com/zsrl/tdxtrader
